catsim/__init__.py
catsim/cat.py
catsim/estimation.py
catsim/initialization.py
catsim/irt.py
catsim/plot.py
catsim/selection.py
catsim/simulation.py
catsim/stopping.py
catsim-0.17.3.dist-info/COPYING
catsim-0.17.3.dist-info/COPYING.LESSER
catsim-0.17.3.dist-info/METADATA
catsim-0.17.3.dist-info/WHEEL
catsim-0.17.3.dist-info/top_level.txt
catsim-0.17.3.dist-info/RECORD
