Metadata-Version: 2.1
Name: catsim
Version: 0.17.3
Summary: Computerized Adaptive Testing Simulator
Author-email: Douglas De Rizzo Meneghetti <douglasrizzo@gmail.com>
License:                    GNU LESSER GENERAL PUBLIC LICENSE
Project-URL: homepage, https://douglasrizzo.com.br/catsim
Classifier: Development Status :: 4 - Beta
Classifier: Intended Audience :: Education
Classifier: Intended Audience :: Science/Research
Classifier: Natural Language :: English
Classifier: Programming Language :: Python :: 3.5
Classifier: Programming Language :: Python :: 3.6
Classifier: Programming Language :: Python :: 3.7
Classifier: Programming Language :: Python :: 3.8
Classifier: Topic :: Education :: Testing
Classifier: License :: OSI Approved :: GNU Lesser General Public License v3 (LGPLv3)
Requires-Python: >=3.5
License-File: COPYING
License-File: COPYING.LESSER
Requires-Dist: scipy
Requires-Dist: numexpr
Requires-Dist: matplotlib
Requires-Dist: scikit-learn
Requires-Dist: json_tricks
Requires-Dist: tqdm
Requires-Dist: numpy
Provides-Extra: dev
Requires-Dist: mypy; extra == "dev"
Requires-Dist: pylama; extra == "dev"
Requires-Dist: autoflake; extra == "dev"
Requires-Dist: yapf; extra == "dev"
Requires-Dist: black; extra == "dev"
Requires-Dist: isort; extra == "dev"
Provides-Extra: testing
Requires-Dist: pytest; extra == "testing"
Requires-Dist: scikit-learn; extra == "testing"
Requires-Dist: flake8; extra == "testing"
Requires-Dist: yapf; extra == "testing"
Provides-Extra: docs
Requires-Dist: Sphinx; extra == "docs"
Requires-Dist: numpydoc; extra == "docs"
Requires-Dist: sphinx_autodoc_annotation; extra == "docs"
Requires-Dist: sphinx_rtd_theme; extra == "docs"
Requires-Dist: m2r2; extra == "docs"
Requires-Dist: bibtex-pygments-lexer; extra == "docs"
Requires-Dist: matplotlib; extra == "docs"
Provides-Extra: upload
Requires-Dist: twine; extra == "upload"
Requires-Dist: build; extra == "upload"
